sources/FLIP-FLOPS/FLIP-FLOP_D.vhd
library IEEE;
use IEEE.std_logic_1164.all;


entity FLIP_FLOP_D is
    port(
        clk: in std_logic;
        d: in std_logic;
        ebl,rst: in std_logic;
        q,nq: out std_logic
    );
end FLIP_FLOP_D;

architecture Behavioral of FLIP_FLOP_D is

signal qa: std_logic:='0';

begin
--FLIP_FLOP D

-- Q	D	Q t+1
-- 0	0	0
-- 0	1	1
-- 1	0	0
-- 1	1	1

-- con reloj

    process (clk,d,ebl,rst)
    begin
        if rising_edge(clk) and ebl='1' then
         
            if qa='0' and d='0' then
                qa<='0';
            elsif qa='0' and d='1' then
                qa<='1';
            elsif qa='1' and d='0' then
                qa<='0';
            elsif qa='1' and d='1' then
                qa<='1';
            end if;
        
        elsif rising_edge(clk) and ebl='1' and rst='1' then
            qa<='0';
            
     end if;
    end process;

    q<=qa;
    nq<=not qa;

    end architecture;

sources/Contadores/Contador_DES.vhd
library IEEE;
use IEEE.std_logic_1164.all;

entity CONTADOR_DES is
    port(
        clk_in, reset: in std_logic;

        q: out std_logic_vector(3 downto 0)
    );
end entity;

architecture CONTADOR_DES of CONTADOR_DES is
    
    signal q_out: std_logic_vector(3 downto 0);
    signal nq_out: std_logic_vector(3 downto 0):= "0000";
    
    begin

    q3: entity work.FLIP_FLOP_D port map(
        clk => q_out(2),
        ebl=> '1',
        rst => reset,
        d => nq_out(3),
        q => q_out(3),
        nq => nq_out(3)

    );

    q2: entity work.FLIP_FLOP_D port map(
        clk => q_out(1),
        ebl=> '1',
        rst => reset,
        d => nq_out(2),
        q => q_out(2),
        nq => nq_out(2)
    );

    q1: entity work.FLIP_FLOP_D port map(
        clk => q_out(0),
        ebl=> '1',
        rst => reset,
        d => nq_out(1),
        q => q_out(1),
        nq => nq_out(1)
    );

    q0: entity work.FLIP_FLOP_D port map(
        clk => clk_in,
        ebl=> '1',
        rst => reset,
        d => nq_out(0),
        q => q_out(0),
        nq => nq_out(0)
    );
    
    q <= q_out;

    end architecture;

sources/Contadores/Contador_AS.vhd
library IEEE;
use IEEE.std_logic_1164.all;

entity CONTADOR_AS is
    port(
        clk_in, reset: in std_logic;

        q: out std_logic_vector(3 downto 0)
    );
end entity;

architecture CONTADOR_AS of CONTADOR_AS is
    
    signal q_out: std_logic_vector(3 downto 0);
    signal nq_out: std_logic_vector(3 downto 0);
    
    begin

    q3: entity work.FLIP_FLOP_D port map(
        clk => nq_out(2),
        ebl=> '1',
        rst => reset,
        d => nq_out(3),
        q => q_out(3),
        nq => nq_out(3)

    );

    q2: entity work.FLIP_FLOP_D port map(
        clk => nq_out(1),
        ebl=> '1',
        rst => reset,
        d => nq_out(2),
        q => q_out(2),
        nq => nq_out(2)
    );

    q1: entity work.FLIP_FLOP_D port map(
        clk => nq_out(0),
        ebl=> '1',
        rst => reset,
        d => nq_out(1),
        q => q_out(1),
        nq => nq_out(1)
    );

    q0: entity work.FLIP_FLOP_D port map(
        clk => clk_in,
        ebl=> '1',
        rst => reset,
        d => nq_out(0),
        q => q_out(0),
        nq => nq_out(0)
    );
    
    q <= q_out;

    end architecture;

sources/Test/testbench-CONT.vhd
library IEEE;
use IEEE.std_logic_1164.all;

entity testbench_CONT is
end entity;

architecture Behavioral of testbench_CONT is
    
    signal clk: std_logic := '0';
    signal rst: std_logic := '0';
    signal q_AS:   std_logic_vector(3 downto 0);
    signal q_DES:   std_logic_vector(3 downto 0);

    constant clk_period: time := 2 sec;

    begin

    Cont_as: entity work.CONTADOR_AS port map(
        clk_in => clk,
        reset => rst,
        
        q=> q_AS
    );

    Cont_des: entity work.CONTADOR_DES port map(
        clk_in => clk,
        reset => rst,
        
        q=> q_DES
    );


        CLK_PROC : process
        begin
        wait for clk_period / 2;
        if clk = '1' then
            clk <= '0';
        else
            clk <= '1';
        end if;
        end process;

       
        end architecture;

sources/Dumps/CONT-dump.vcd
$date
  Tue Apr 25 22:43:23 2023
$end
$version
  GHDL v0
$end
$timescale
  1 fs
$end
$scope module standard $end
$upscope $end
$scope module std_logic_1164 $end
$upscope $end
$scope module testbench_cont $end
$var reg 1 ! clk $end
$var reg 1 " rst $end
$var reg 4 # q_as[3:0] $end
$var reg 4 $ q_des[3:0] $end
$scope module cont_as $end
$var reg 1 % clk_in $end
$var reg 1 & reset $end
$var reg 4 ' q[3:0] $end
$var reg 4 ( q_out[3:0] $end
$var reg 4 ) nq_out[3:0] $end
$scope module q3 $end
$var reg 1 * clk $end
$var reg 1 + d $end
$var reg 1 , ebl $end
$var reg 1 - rst $end
$var reg 1 . q $end
$var reg 1 / nq $end
$var reg 1 0 qa $end
$upscope $end
$scope module q2 $end
$var reg 1 1 clk $end
$var reg 1 2 d $end
$var reg 1 3 ebl $end
$var reg 1 4 rst $end
$var reg 1 5 q $end
$var reg 1 6 nq $end
$var reg 1 7 qa $end
$upscope $end
$scope module q1 $end
$var reg 1 8 clk $end
$var reg 1 9 d $end
$var reg 1 : ebl $end
$var reg 1 ; rst $end
$var reg 1 < q $end
$var reg 1 = nq $end
$var reg 1 > qa $end
$upscope $end
$scope module q0 $end
$var reg 1 ? clk $end
$var reg 1 @ d $end
$var reg 1 A ebl $end
$var reg 1 B rst $end
$var reg 1 C q $end
$var reg 1 D nq $end
$var reg 1 E qa $end
$upscope $end
$upscope $end
$scope module cont_des $end
$var reg 1 F clk_in $end
$var reg 1 G reset $end
$var reg 4 H q[3:0] $end
$var reg 4 I q_out[3:0] $end
$var reg 4 J nq_out[3:0] $end
$scope module q3 $end
$var reg 1 K clk $end
$var reg 1 L d $end
$var reg 1 M ebl $end
$var reg 1 N rst $end
$var reg 1 O q $end
$var reg 1 P nq $end
$var reg 1 Q qa $end
$upscope $end
$scope module q2 $end
$var reg 1 R clk $end
$var reg 1 S d $end
$var reg 1 T ebl $end
$var reg 1 U rst $end
$var reg 1 V q $end
$var reg 1 W nq $end
$var reg 1 X qa $end
$upscope $end
$scope module q1 $end
$var reg 1 Y clk $end
$var reg 1 Z d $end
$var reg 1 [ ebl $end
$var reg 1 \ rst $end
$var reg 1 ] q $end
$var reg 1 ^ nq $end
$var reg 1 _ qa $end
$upscope $end
$scope module q0 $end
$var reg 1 ` clk $end
$var reg 1 a d $end
$var reg 1 b ebl $end
$var reg 1 c rst $end
$var reg 1 d q $end
$var reg 1 e nq $end
$var reg 1 f qa $end
$upscope $end
$upscope $end
$upscope $end
$enddefinitions $end
#0
0!
0"
b0000 #
b0000 $
0%
0&
b0000 '
b0000 (
b1111 )
1*
1+
1,
0-
0.
1/
00
11
12
13
04
05
16
07
18
19
1:
0;
0<
1=
0>
0?
1@
1A
0B
0C
1D
0E
0F
0G
b0000 H
b0000 I
b1111 J
0K
1L
1M
0N
0O
1P
0Q
0R
1S
1T
0U
0V
1W
0X
0Y
1Z
1[
0\
0]
1^
0_
0`
1a
1b
0c
0d
1e
0f
#1000000000000000
1!
b0001 #
b1111 $
1%
b0001 '
b0001 (
b1110 )
08
1?
0@
1C
0D
1E
1F
b1111 H
b1111 I
b0000 J
1K
0L
1O
0P
1Q
1R
0S
1V
0W
1X
1Y
0Z
1]
0^
1_
1`
0a
1d
0e
1f
#2000000000000000
0!
0%
0?
0F
0`
#3000000000000000
1!
b0010 #
b1110 $
1%
b0010 '
b0010 (
b1101 )
01
18
09
1<
0=
1>
1?
1@
0C
1D
0E
1F
b1110 H
b1110 I
b0001 J
0Y
1`
1a
0d
1e
0f
#4000000000000000
0!
0%
0?
0F
0`
#5000000000000000
1!
b0011 #
b1101 $
1%
b0011 '
b0011 (
b1100 )
08
1?
0@
1C
0D
1E
1F
b1101 H
b1101 I
b0010 J
0R
1Y
1Z
0]
1^
0_
1`
0a
1d
0e
1f
#6000000000000000
0!
0%
0?
0F
0`
#7000000000000000
1!
b0100 #
b1100 $
1%
b0100 '
b0100 (
b1011 )
0*
11
02
15
06
17
18
19
0<
1=
0>
1?
1@
0C
1D
0E
1F
b1100 H
b1100 I
b0011 J
0Y
1`
1a
0d
1e
0f
#8000000000000000
0!
0%
0?
0F
0`
#9000000000000000
1!
b0101 #
b1011 $
1%
b0101 '
b0101 (
b1010 )
08
1?
0@
1C
0D
1E
1F
b1011 H
b1011 I
b0100 J
0K
1R
1S
0V
1W
0X
1Y
0Z
1]
0^
1_
1`
0a
1d
0e
1f
#10000000000000000
0!
0%
0?
0F
0`
#11000000000000000
1!
b0110 #
b1010 $
1%
b0110 '
b0110 (
b1001 )
01
18
09
1<
0=
1>
1?
1@
0C
1D
0E
1F
b1010 H
b1010 I
b0101 J
0Y
1`
1a
0d
1e
0f
#12000000000000000
0!
0%
0?
0F
0`
#13000000000000000
1!
b0111 #
b1001 $
1%
b0111 '
b0111 (
b1000 )
08
1?
0@
1C
0D
1E
1F
b1001 H
b1001 I
b0110 J
0R
1Y
1Z
0]
1^
0_
1`
0a
1d
0e
1f
#14000000000000000
0!
0%
0?
0F
0`
#15000000000000000
1!
b1000 #
b1000 $
1%
b1000 '
b1000 (
b0111 )
1*
0+
1.
0/
10
11
12
05
16
07
18
19
0<
1=
0>
1?
1@
0C
1D
0E
1F
b1000 H
b1000 I
b0111 J
0Y
1`
1a
0d
1e
0f
#16000000000000000
0!
0%
0?
0F
0`
#17000000000000000
1!
b1001 #
b0111 $
1%
b1001 '
b1001 (
b0110 )
08
1?
0@
1C
0D
1E
1F
b0111 H
b0111 I
b1000 J
1K
1L
0O
1P
0Q
1R
0S
1V
0W
1X
1Y
0Z
1]
0^
1_
1`
0a
1d
0e
1f
#18000000000000000
0!
0%
0?
0F
0`
#19000000000000000
1!
b1010 #
b0110 $
1%
b1010 '
b1010 (
b0101 )
01
18
09
1<
0=
1>
1?
1@
0C
1D
0E
1F
b0110 H
b0110 I
b1001 J
0Y
1`
1a
0d
1e
0f
#20000000000000000
0!
0%
0?
0F
0`
#21000000000000000
1!
b1011 #
b0101 $
1%
b1011 '
b1011 (
b0100 )
08
1?
0@
1C
0D
1E
1F
b0101 H
b0101 I
b1010 J
0R
1Y
1Z
0]
1^
0_
1`
0a
1d
0e
1f
#22000000000000000
0!
0%
0?
0F
0`
#23000000000000000
1!
b1100 #
b0100 $
1%
b1100 '
b1100 (
b0011 )
0*
11
02
15
06
17
18
19
0<
1=
0>
1?
1@
0C
1D
0E
1F
b0100 H
b0100 I
b1011 J
0Y
1`
1a
0d
1e
0f
#24000000000000000
0!
0%
0?
0F
0`
#25000000000000000
1!
b1101 #
b0011 $
1%
b1101 '
b1101 (
b0010 )
08
1?
0@
1C
0D
1E
1F
b0011 H
b0011 I
b1100 J
0K
1R
1S
0V
1W
0X
1Y
0Z
1]
0^
1_
1`
0a
1d
0e
1f
#26000000000000000
0!
0%
0?
0F
0`
#27000000000000000
1!
b1110 #
b0010 $
1%
b1110 '
b1110 (
b0001 )
01
18
09
1<
0=
1>
1?
1@
0C
1D
0E
1F
b0010 H
b0010 I
b1101 J
0Y
1`
1a
0d
1e
0f
#28000000000000000
0!
0%
0?
0F
0`
#29000000000000000
1!
b1111 #
b0001 $
1%
b1111 '
b1111 (
b0000 )
08
1?
0@
1C
0D
1E
1F
b0001 H
b0001 I
b1110 J
0R
1Y
1Z
0]
1^
0_
1`
0a
1d
0e
1f
#30000000000000000
0!
0%
0?
0F
0`
#31000000000000000
1!
b0000 #
b0000 $
1%
b0000 '
b0000 (
b1111 )
1*
1+
0.
1/
00
11
12
05
16
07
18
19
0<
1=
0>
1?
1@
0C
1D
0E
1F
b0000 H
b0000 I
b1111 J
0Y
1`
1a
0d
1e
0f
#32000000000000000
0!
0%
0?
0F
0`
#33000000000000000
1!
b0001 #
b1111 $
1%
b0001 '
b0001 (
b1110 )
08
1?
0@
1C
0D
1E
1F
b1111 H
b1111 I
b0000 J
1K
0L
1O
0P
1Q
1R
0S
1V
0W
1X
1Y
0Z
1]
0^
1_
1`
0a
1d
0e
1f
#34000000000000000
0!
0%
0?
0F
0`
#35000000000000000
1!
b0010 #
b1110 $
1%
b0010 '
b0010 (
b1101 )
01
18
09
1<
0=
1>
1?
1@
0C
1D
0E
1F
b1110 H
b1110 I
b0001 J
0Y
1`
1a
0d
1e
0f
#36000000000000000
0!
0%
0?
0F
0`
#37000000000000000
1!
b0011 #
b1101 $
1%
b0011 '
b0011 (
b1100 )
08
1?
0@
1C
0D
1E
1F
b1101 H
b1101 I
b0010 J
0R
1Y
1Z
0]
1^
0_
1`
0a
1d
0e
1f
#38000000000000000
0!
0%
0?
0F
0`
#39000000000000000
1!
b0100 #
b1100 $
1%
b0100 '
b0100 (
b1011 )
0*
11
02
15
06
17
18
19
0<
1=
0>
1?
1@
0C
1D
0E
1F
b1100 H
b1100 I
b0011 J
0Y
1`
1a
0d
1e
0f
#40000000000000000
0!
0%
0?
0F
0`
#41000000000000000
1!
b0101 #
b1011 $
1%
b0101 '
b0101 (
b1010 )
08
1?
0@
1C
0D
1E
1F
b1011 H
b1011 I
b0100 J
0K
1R
1S
0V
1W
0X
1Y
0Z
1]
0^
1_
1`
0a
1d
0e
1f
#42000000000000000
0!
0%
0?
0F
0`
#43000000000000000
1!
b0110 #
b1010 $
1%
b0110 '
b0110 (
b1001 )
01
18
09
1<
0=
1>
1?
1@
0C
1D
0E
1F
b1010 H
b1010 I
b0101 J
0Y
1`
1a
0d
1e
0f
#44000000000000000
0!
0%
0?
0F
0`
#45000000000000000
1!
b0111 #
b1001 $
1%
b0111 '
b0111 (
b1000 )
08
1?
0@
1C
0D
1E
1F
b1001 H
b1001 I
b0110 J
0R
1Y
1Z
0]
1^
0_
1`
0a
1d
0e
1f
#46000000000000000
0!
0%
0?
0F
0`
#47000000000000000
1!
b1000 #
b1000 $
1%
b1000 '
b1000 (
b0111 )
1*
0+
1.
0/
10
11
12
05
16
07
18
19
0<
1=
0>
1?
1@
0C
1D
0E
1F
b1000 H
b1000 I
b0111 J
0Y
1`
1a
0d
1e
0f
#48000000000000000
0!
0%
0?
0F
0`
#49000000000000000
1!
b1001 #
b0111 $
1%
b1001 '
b1001 (
b0110 )
08
1?
0@
1C
0D
1E
1F
b0111 H
b0111 I
b1000 J
1K
1L
0O
1P
0Q
1R
0S
1V
0W
1X
1Y
0Z
1]
0^
1_
1`
0a
1d
0e
1f
#50000000000000000
0!
0%
0?
0F
0`
#51000000000000000
1!
b1010 #
b0110 $
1%
b1010 '
b1010 (
b0101 )
01
18
09
1<
0=
1>
1?
1@
0C
1D
0E
1F
b0110 H
b0110 I
b1001 J
0Y
1`
1a
0d
1e
0f
#52000000000000000
0!
0%
0?
0F
0`
#53000000000000000
1!
b1011 #
b0101 $
1%
b1011 '
b1011 (
b0100 )
08
1?
0@
1C
0D
1E
1F
b0101 H
b0101 I
b1010 J
0R
1Y
1Z
0]
1^
0_
1`
0a
1d
0e
1f
#54000000000000000
0!
0%
0?
0F
0`
#55000000000000000
1!
b1100 #
b0100 $
1%
b1100 '
b1100 (
b0011 )
0*
11
02
15
06
17
18
19
0<
1=
0>
1?
1@
0C
1D
0E
1F
b0100 H
b0100 I
b1011 J
0Y
1`
1a
0d
1e
0f
#56000000000000000
0!
0%
0?
0F
0`
#57000000000000000
1!
b1101 #
b0011 $
1%
b1101 '
b1101 (
b0010 )
08
1?
0@
1C
0D
1E
1F
b0011 H
b0011 I
b1100 J
0K
1R
1S
0V
1W
0X
1Y
0Z
1]
0^
1_
1`
0a
1d
0e
1f
#58000000000000000
0!
0%
0?
0F
0`
#59000000000000000
1!
b1110 #
b0010 $
1%
b1110 '
b1110 (
b0001 )
01
18
09
1<
0=
1>
1?
1@
0C
1D
0E
1F
b0010 H
b0010 I
b1101 J
0Y
1`
1a
0d
1e
0f
#60000000000000000
0!
0%
0?
0F
0`
#61000000000000000
1!
b1111 #
b0001 $
1%
b1111 '
b1111 (
b0000 )
08
1?
0@
1C
0D
1E
1F
b0001 H
b0001 I
b1110 J
0R
1Y
1Z
0]
1^
0_
1`
0a
1d
0e
1f
#62000000000000000
0!
0%
0?
0F
0`
#63000000000000000
1!
b0000 #
b0000 $
1%
b0000 '
b0000 (
b1111 )
1*
1+
0.
1/
00
11
12
05
16
07
18
19
0<
1=
0>
1?
1@
0C
1D
0E
1F
b0000 H
b0000 I
b1111 J
0Y
1`
1a
0d
1e
0f
#64000000000000000
0!
0%
0?
0F
0`
#65000000000000000
1!
b0001 #
b1111 $
1%
b0001 '
b0001 (
b1110 )
08
1?
0@
1C
0D
1E
1F
b1111 H
b1111 I
b0000 J
1K
0L
1O
0P
1Q
1R
0S
1V
0W
1X
1Y
0Z
1]
0^
1_
1`
0a
1d
0e
1f
#66000000000000000
0!
0%
0?
0F
0`
#67000000000000000
1!
b0010 #
b1110 $
1%
b0010 '
b0010 (
b1101 )
01
18
09
1<
0=
1>
1?
1@
0C
1D
0E
1F
b1110 H
b1110 I
b0001 J
0Y
1`
1a
0d
1e
0f
#68000000000000000
0!
0%
0?
0F
0`
#69000000000000000
1!
b0011 #
b1101 $
1%
b0011 '
b0011 (
b1100 )
08
1?
0@
1C
0D
1E
1F
b1101 H
b1101 I
b0010 J
0R
1Y
1Z
0]
1^
0_
1`
0a
1d
0e
1f
#70000000000000000
0!
0%
0?
0F
0`
#71000000000000000
1!
b0100 #
b1100 $
1%
b0100 '
b0100 (
b1011 )
0*
11
02
15
06
17
18
19
0<
1=
0>
1?
1@
0C
1D
0E
1F
b1100 H
b1100 I
b0011 J
0Y
1`
1a
0d
1e
0f
#72000000000000000
0!
0%
0?
0F
0`
#73000000000000000
1!
b0101 #
b1011 $
1%
b0101 '
b0101 (
b1010 )
08
1?
0@
1C
0D
1E
1F
b1011 H
b1011 I
b0100 J
0K
1R
1S
0V
1W
0X
1Y
0Z
1]
0^
1_
1`
0a
1d
0e
1f
#74000000000000000
0!
0%
0?
0F
0`
#75000000000000000
1!
b0110 #
b1010 $
1%
b0110 '
b0110 (
b1001 )
01
18
09
1<
0=
1>
1?
1@
0C
1D
0E
1F
b1010 H
b1010 I
b0101 J
0Y
1`
1a
0d
1e
0f
#76000000000000000
0!
0%
0?
0F
0`
#77000000000000000
1!
b0111 #
b1001 $
1%
b0111 '
b0111 (
b1000 )
08
1?
0@
1C
0D
1E
1F
b1001 H
b1001 I
b0110 J
0R
1Y
1Z
0]
1^
0_
1`
0a
1d
0e
1f
#78000000000000000
0!
0%
0?
0F
0`
#79000000000000000
1!
b1000 #
b1000 $
1%
b1000 '
b1000 (
b0111 )
1*
0+
1.
0/
10
11
12
05
16
07
18
19
0<
1=
0>
1?
1@
0C
1D
0E
1F
b1000 H
b1000 I
b0111 J
0Y
1`
1a
0d
1e
0f
#80000000000000000
0!
0%
0?
0F
0`
#81000000000000000
1!
b1001 #
b0111 $
1%
b1001 '
b1001 (
b0110 )
08
1?
0@
1C
0D
1E
1F
b0111 H
b0111 I
b1000 J
1K
1L
0O
1P
0Q
1R
0S
1V
0W
1X
1Y
0Z
1]
0^
1_
1`
0a
1d
0e
1f
#82000000000000000
0!
0%
0?
0F
0`
#83000000000000000
1!
b1010 #
b0110 $
1%
b1010 '
b1010 (
b0101 )
01
18
09
1<
0=
1>
1?
1@
0C
1D
0E
1F
b0110 H
b0110 I
b1001 J
0Y
1`
1a
0d
1e
0f
#84000000000000000
0!
0%
0?
0F
0`
#85000000000000000
1!
b1011 #
b0101 $
1%
b1011 '
b1011 (
b0100 )
08
1?
0@
1C
0D
1E
1F
b0101 H
b0101 I
b1010 J
0R
1Y
1Z
0]
1^
0_
1`
0a
1d
0e
1f
#86000000000000000
0!
0%
0?
0F
0`
#87000000000000000
1!
b1100 #
b0100 $
1%
b1100 '
b1100 (
b0011 )
0*
11
02
15
06
17
18
19
0<
1=
0>
1?
1@
0C
1D
0E
1F
b0100 H
b0100 I
b1011 J
0Y
1`
1a
0d
1e
0f
#88000000000000000
0!
0%
0?
0F
0`
#89000000000000000
1!
b1101 #
b0011 $
1%
b1101 '
b1101 (
b0010 )
08
1?
0@
1C
0D
1E
1F
b0011 H
b0011 I
b1100 J
0K
1R
1S
0V
1W
0X
1Y
0Z
1]
0^
1_
1`
0a
1d
0e
1f
#90000000000000000
0!
0%
0?
0F
0`
#91000000000000000
1!
b1110 #
b0010 $
1%
b1110 '
b1110 (
b0001 )
01
18
09
1<
0=
1>
1?
1@
0C
1D
0E
1F
b0010 H
b0010 I
b1101 J
0Y
1`
1a
0d
1e
0f
#92000000000000000
0!
0%
0?
0F
0`
#93000000000000000
1!
b1111 #
b0001 $
1%
b1111 '
b1111 (
b0000 )
08
1?
0@
1C
0D
1E
1F
b0001 H
b0001 I
b1110 J
0R
1Y
1Z
0]
1^
0_
1`
0a
1d
0e
1f
#94000000000000000
0!
0%
0?
0F
0`
#95000000000000000
1!
b0000 #
b0000 $
1%
b0000 '
b0000 (
b1111 )
1*
1+
0.
1/
00
11
12
05
16
07
18
19
0<
1=
0>
1?
1@
0C
1D
0E
1F
b0000 H
b0000 I
b1111 J
0Y
1`
1a
0d
1e
0f
#96000000000000000
0!
0%
0?
0F
0`
#97000000000000000
1!
b0001 #
b1111 $
1%
b0001 '
b0001 (
b1110 )
08
1?
0@
1C
0D
1E
1F
b1111 H
b1111 I
b0000 J
1K
0L
1O
0P
1Q
1R
0S
1V
0W
1X
1Y
0Z
1]
0^
1_
1`
0a
1d
0e
1f
#98000000000000000
0!
0%
0?
0F
0`
#99000000000000000
1!
b0010 #
b1110 $
1%
b0010 '
b0010 (
b1101 )
01
18
09
1<
0=
1>
1?
1@
0C
1D
0E
1F
b1110 H
b1110 I
b0001 J
0Y
1`
1a
0d
1e
0f
#100000000000000000
0!
0%
0?
0F
0`
#101000000000000000
1!
b0011 #
b1101 $
1%
b0011 '
b0011 (
b1100 )
08
1?
0@
1C
0D
1E
1F
b1101 H
b1101 I
b0010 J
0R
1Y
1Z
0]
1^
0_
1`
0a
1d
0e
1f
#102000000000000000
0!
0%
0?
0F
0`
#103000000000000000
1!
b0100 #
b1100 $
1%
b0100 '
b0100 (
b1011 )
0*
11
02
15
06
17
18
19
0<
1=
0>
1?
1@
0C
1D
0E
1F
b1100 H
b1100 I
b0011 J
0Y
1`
1a
0d
1e
0f
#104000000000000000
0!
0%
0?
0F
0`
#105000000000000000
1!
b0101 #
b1011 $
1%
b0101 '
b0101 (
b1010 )
08
1?
0@
1C
0D
1E
1F
b1011 H
b1011 I
b0100 J
0K
1R
1S
0V
1W
0X
1Y
0Z
1]
0^
1_
1`
0a
1d
0e
1f
#106000000000000000
0!
0%
0?
0F
0`
#107000000000000000
1!
b0110 #
b1010 $
1%
b0110 '
b0110 (
b1001 )
01
18
09
1<
0=
1>
1?
1@
0C
1D
0E
1F
b1010 H
b1010 I
b0101 J
0Y
1`
1a
0d
1e
0f
#108000000000000000
0!
0%
0?
0F
0`
#109000000000000000
1!
b0111 #
b1001 $
1%
b0111 '
b0111 (
b1000 )
08
1?
0@
1C
0D
1E
1F
b1001 H
b1001 I
b0110 J
0R
1Y
1Z
0]
1^
0_
1`
0a
1d
0e
1f
#110000000000000000
0!
0%
0?
0F
0`
#111000000000000000
1!
b1000 #
b1000 $
1%
b1000 '
b1000 (
b0111 )
1*
0+
1.
0/
10
11
12
05
16
07
18
19
0<
1=
0>
1?
1@
0C
1D
0E
1F
b1000 H
b1000 I
b0111 J
0Y
1`
1a
0d
1e
0f
#112000000000000000
0!
0%
0?
0F
0`
#113000000000000000
1!
b1001 #
b0111 $
1%
b1001 '
b1001 (
b0110 )
08
1?
0@
1C
0D
1E
1F
b0111 H
b0111 I
b1000 J
1K
1L
0O
1P
0Q
1R
0S
1V
0W
1X
1Y
0Z
1]
0^
1_
1`
0a
1d
0e
1f
#114000000000000000
0!
0%
0?
0F
0`
#115000000000000000
1!
b1010 #
b0110 $
1%
b1010 '
b1010 (
b0101 )
01
18
09
1<
0=
1>
1?
1@
0C
1D
0E
1F
b0110 H
b0110 I
b1001 J
0Y
1`
1a
0d
1e
0f
#116000000000000000
0!
0%
0?
0F
0`
#117000000000000000
1!
b1011 #
b0101 $
1%
b1011 '
b1011 (
b0100 )
08
1?
0@
1C
0D
1E
1F
b0101 H
b0101 I
b1010 J
0R
1Y
1Z
0]
1^
0_
1`
0a
1d
0e
1f
#118000000000000000
0!
0%
0?
0F
0`
#119000000000000000
1!
b1100 #
b0100 $
1%
b1100 '
b1100 (
b0011 )
0*
11
02
15
06
17
18
19
0<
1=
0>
1?
1@
0C
1D
0E
1F
b0100 H
b0100 I
b1011 J
0Y
1`
1a
0d
1e
0f
#120000000000000000
0!
0%
0?
0F
0`
#121000000000000000
1!
b1101 #
b0011 $
1%
b1101 '
b1101 (
b0010 )
08
1?
0@
1C
0D
1E
1F
b0011 H
b0011 I
b1100 J
0K
1R
1S
0V
1W
0X
1Y
0Z
1]
0^
1_
1`
0a
1d
0e
1f
#122000000000000000
0!
0%
0?
0F
0`
#123000000000000000
1!
b1110 #
b0010 $
1%
b1110 '
b1110 (
b0001 )
01
18
09
1<
0=
1>
1?
1@
0C
1D
0E
1F
b0010 H
b0010 I
b1101 J
0Y
1`
1a
0d
1e
0f
#124000000000000000
0!
0%
0?
0F
0`
#125000000000000000
1!
b1111 #
b0001 $
1%
b1111 '
b1111 (
b0000 )
08
1?
0@
1C
0D
1E
1F
b0001 H
b0001 I
b1110 J
0R
1Y
1Z
0]
1^
0_
1`
0a
1d
0e
1f
#126000000000000000
0!
0%
0?
0F
0`
#127000000000000000
1!
b0000 #
b0000 $
1%
b0000 '
b0000 (
b1111 )
1*
1+
0.
1/
00
11
12
05
16
07
18
19
0<
1=
0>
1?
1@
0C
1D
0E
1F
b0000 H
b0000 I
b1111 J
0Y
1`
1a
0d
1e
0f
#128000000000000000
0!
0%
0?
0F
0`
#129000000000000000
1!
b0001 #
b1111 $
1%
b0001 '
b0001 (
b1110 )
08
1?
0@
1C
0D
1E
1F
b1111 H
b1111 I
b0000 J
1K
0L
1O
0P
1Q
1R
0S
1V
0W
1X
1Y
0Z
1]
0^
1_
1`
0a
1d
0e
1f
#130000000000000000
0!
0%
0?
0F
0`
#131000000000000000
1!
b0010 #
b1110 $
1%
b0010 '
b0010 (
b1101 )
01
18
09
1<
0=
1>
1?
1@
0C
1D
0E
1F
b1110 H
b1110 I
b0001 J
0Y
1`
1a
0d
1e
0f
#132000000000000000
0!
0%
0?
0F
0`
#133000000000000000
1!
b0011 #
b1101 $
1%
b0011 '
b0011 (
b1100 )
08
1?
0@
1C
0D
1E
1F
b1101 H
b1101 I
b0010 J
0R
1Y
1Z
0]
1^
0_
1`
0a
1d
0e
1f
#134000000000000000
0!
0%
0?
0F
0`
#135000000000000000
1!
b0100 #
b1100 $
1%
b0100 '
b0100 (
b1011 )
0*
11
02
15
06
17
18
19
0<
1=
0>
1?
1@
0C
1D
0E
1F
b1100 H
b1100 I
b0011 J
0Y
1`
1a
0d
1e
0f
#136000000000000000
0!
0%
0?
0F
0`
#137000000000000000
1!
b0101 #
b1011 $
1%
b0101 '
b0101 (
b1010 )
08
1?
0@
1C
0D
1E
1F
b1011 H
b1011 I
b0100 J
0K
1R
1S
0V
1W
0X
1Y
0Z
1]
0^
1_
1`
0a
1d
0e
1f
#138000000000000000
0!
0%
0?
0F
0`
#139000000000000000
1!
b0110 #
b1010 $
1%
b0110 '
b0110 (
b1001 )
01
18
09
1<
0=
1>
1?
1@
0C
1D
0E
1F
b1010 H
b1010 I
b0101 J
0Y
1`
1a
0d
1e
0f
#140000000000000000
0!
0%
0?
0F
0`
#141000000000000000
1!
b0111 #
b1001 $
1%
b0111 '
b0111 (
b1000 )
08
1?
0@
1C
0D
1E
1F
b1001 H
b1001 I
b0110 J
0R
1Y
1Z
0]
1^
0_
1`
0a
1d
0e
1f
#142000000000000000
0!
0%
0?
0F
0`
#143000000000000000
1!
b1000 #
b1000 $
1%
b1000 '
b1000 (
b0111 )
1*
0+
1.
0/
10
11
12
05
16
07
18
19
0<
1=
0>
1?
1@
0C
1D
0E
1F
b1000 H
b1000 I
b0111 J
0Y
1`
1a
0d
1e
0f
#144000000000000000
0!
0%
0?
0F
0`
#145000000000000000
1!
b1001 #
b0111 $
1%
b1001 '
b1001 (
b0110 )
08
1?
0@
1C
0D
1E
1F
b0111 H
b0111 I
b1000 J
1K
1L
0O
1P
0Q
1R
0S
1V
0W
1X
1Y
0Z
1]
0^
1_
1`
0a
1d
0e
1f
#146000000000000000
0!
0%
0?
0F
0`
#147000000000000000
1!
b1010 #
b0110 $
1%
b1010 '
b1010 (
b0101 )
01
18
09
1<
0=
1>
1?
1@
0C
1D
0E
1F
b0110 H
b0110 I
b1001 J
0Y
1`
1a
0d
1e
0f
#148000000000000000
0!
0%
0?
0F
0`
#149000000000000000
1!
b1011 #
b0101 $
1%
b1011 '
b1011 (
b0100 )
08
1?
0@
1C
0D
1E
1F
b0101 H
b0101 I
b1010 J
0R
1Y
1Z
0]
1^
0_
1`
0a
1d
0e
1f
#150000000000000000
0!
0%
0?
0F
0`
#151000000000000000
1!
b1100 #
b0100 $
1%
b1100 '
b1100 (
b0011 )
0*
11
02
15
06
17
18
19
0<
1=
0>
1?
1@
0C
1D
0E
1F
b0100 H
b0100 I
b1011 J
0Y
1`
1a
0d
1e
0f
#152000000000000000
0!
0%
0?
0F
0`
#153000000000000000
1!
b1101 #
b0011 $
1%
b1101 '
b1101 (
b0010 )
08
1?
0@
1C
0D
1E
1F
b0011 H
b0011 I
b1100 J
0K
1R
1S
0V
1W
0X
1Y
0Z
1]
0^
1_
1`
0a
1d
0e
1f
#154000000000000000
0!
0%
0?
0F
0`
#155000000000000000
1!
b1110 #
b0010 $
1%
b1110 '
b1110 (
b0001 )
01
18
09
1<
0=
1>
1?
1@
0C
1D
0E
1F
b0010 H
b0010 I
b1101 J
0Y
1`
1a
0d
1e
0f
