sources/div_freq.vhd
library IEEE;
use IEEE.STD_LOGIC_1164.ALL;

entity Divisor_frecuencia is
    Port (
        Clk : in STD_LOGIC;
        CLK_o : out STD_LOGIC
        );
end Divisor_frecuencia;    

architecture Behavioral of Divisor_frecuencia is

signal Divisor : integer range 0 to 100;
signal CLKo : STD_LOGIC;
-- La definición de la variable Divisor se
-- definición de la Arquitectura

begin
 
 div:process(Clk)
 begin

if (Clk'event and Clk='1') then
    if(Divisor = 100)then 
        Divisor<=0;
        CLKo <= not CLKo;
    else
        Divisor <= Divisor + 1;
    end if; 
CLK_o <= CLKo;
end if;

end Process div;
    
    end Behavioral;

sources/FLIP-FLOP_NAND.vhd
library IEEE;
use IEEE.std_logic_1164.all;


entity FLIP_FLOP is
    port(
        clk: in std_logic;
        rs: in std_logic_vector(1 downto 0);
        qo: out std_logic_vector(1 downto 0)
        
    );
end FLIP_FLOP;

architecture Behavioral of FLIP_FLOP is

signal q: std_logic_vector(1 downto 0):="00";

begin
--FLIP_FLOP NAND

-- NAND			
-- R	S	Q	Q'
-- 0	0	Unknown	
-- 0	1	0	1
-- 1	0	1	0
-- 1	1	Memory

-- Sin reloj
    -- q<= "01" WHEN rs="01" ELSE
    --     "10" WHEN rs="10" ELSE
    --     q WHEN rs="11";

    -- qo<=q;

-- con reloj

    process (clk)
    begin
        if rising_edge(clk) then
            
            if rs="01" then 
            q<="01";
        elsif rs="10" then
            q<="10";
        elsif rs="11" then
            q<=q;
        end if;
            end if;
    end process;
    qo<=q;

    end architecture;

sources/testbench.vhd
library IEEE;
use IEEE.std_logic_1164.all;


entity testbench is
end testbench;

architecture Behavioral of testbench is

    signal q_out, rs_in: std_logic_vector(1 downto 0):="00";
    signal clk : std_logic:= '0';
    signal clk_out : std_logic;
    constant clk_hz : integer := 1;
    constant clk_period : time := 1 sec / clk_hz;

begin
    
    fp: entity work.FLIP_FLOP port map(
        
        clk=>clk,    
        rs=>rs_in,
        qo=>q_out
    );

    div: entity work.Divisor_frecuencia port map(
        Clk=>clk,
        CLK_o=>clk_out
    );
 
    CLK_PROC : process
begin
  wait for clk_period / 2;
  if clk = '1' then
    clk <= '0';
  else
    clk <= '1';
  end if;
end process;


    process
    begin
        wait for 499 ms;
        rs_in <= "01"; 
    wait for 1000 ms;
report "q: " & std_logic'image(q_out(1)) & std_logic'image(q_out(0));

rs_in <= "11"; 
wait for 1000 ms;
report "q: " & std_logic'image(q_out(1)) & std_logic'image(q_out(0));

rs_in <= "10"; 
wait for 1000 ms;
report "q: " & std_logic'image(q_out(1)) & std_logic'image(q_out(0));

rs_in <= "00"; 
wait for 1000 ms;
assert false report "Test Done." severity note;
    wait;

    end process;

    end Behavioral;

sources/dump.vcd
$date
  Wed Apr 19 00:45:10 2023
$end
$version
  GHDL v0
$end
$timescale
  1 fs
$end
$scope module standard $end
$upscope $end
$scope module std_logic_1164 $end
$upscope $end
$scope module testbench $end
$var reg 2 ! q_out[1:0] $end
$var reg 2 " rs_in[1:0] $end
$var reg 1 # clk $end
$var reg 1 $ clk_out $end
$scope module fp $end
$var reg 1 % clk $end
$var reg 2 & rs[1:0] $end
$var reg 2 ' qo[1:0] $end
$var reg 2 ( q[1:0] $end
$upscope $end
$scope module div $end
$var reg 1 ) clk $end
$var reg 1 * clk_o $end
$var integer 32 + divisor $end
$var reg 1 , clko $end
$upscope $end
$upscope $end
$enddefinitions $end
#0
b00 !
b00 "
0#
U$
0%
b00 &
b00 '
b00 (
0)
U*
b0 +
U,
#499000000000000
b01 "
b01 &
#500000000000000
b01 !
1#
1%
b01 '
b01 (
1)
b1 +
#1000000000000000
0#
0%
0)
#1499000000000000
b11 "
b11 &
#1500000000000000
1#
1%
1)
b10 +
#2000000000000000
0#
0%
0)
#2499000000000000
b10 "
b10 &
#2500000000000000
b10 !
1#
1%
b10 '
b10 (
1)
b11 +
#3000000000000000
0#
0%
0)
#3499000000000000
b00 "
b00 &
#3500000000000000
1#
1%
1)
b100 +
#4000000000000000
0#
0%
0)
#4499000000000000
#4500000000000000
1#
1%
1)
b101 +
#5000000000000000
0#
0%
0)
#5500000000000000
1#
1%
1)
b110 +
#6000000000000000
0#
0%
0)
#6500000000000000
1#
1%
1)
b111 +
#7000000000000000
0#
0%
0)
#7500000000000000
1#
1%
1)
b1000 +
#8000000000000000
0#
0%
0)
#8500000000000000
1#
1%
1)
b1001 +
#9000000000000000
0#
0%
0)
#9500000000000000
1#
1%
1)
b1010 +
#10000000000000000
0#
0%
0)
#10500000000000000
1#
1%
1)
b1011 +
#11000000000000000
0#
0%
0)
#11500000000000000
1#
1%
1)
b1100 +
#12000000000000000
0#
0%
0)
#12500000000000000
1#
1%
1)
b1101 +
#13000000000000000
0#
0%
0)
#13500000000000000
1#
1%
1)
b1110 +
#14000000000000000
0#
0%
0)
#14500000000000000
1#
1%
1)
b1111 +
#15000000000000000
0#
0%
0)
#15500000000000000
1#
1%
1)
b10000 +
#16000000000000000
0#
0%
0)
#16500000000000000
1#
1%
1)
b10001 +
#17000000000000000
0#
0%
0)
#17500000000000000
1#
1%
1)
b10010 +
#18000000000000000
0#
0%
0)
#18500000000000000
1#
1%
1)
b10011 +
#19000000000000000
0#
0%
0)
#19500000000000000
1#
1%
1)
b10100 +
#20000000000000000
0#
0%
0)
#20500000000000000
1#
1%
1)
b10101 +
#21000000000000000
0#
0%
0)
#21500000000000000
1#
1%
1)
b10110 +
#22000000000000000
0#
0%
0)
#22500000000000000
1#
1%
1)
b10111 +
#23000000000000000
0#
0%
0)
#23500000000000000
1#
1%
1)
b11000 +
#24000000000000000
0#
0%
0)
#24500000000000000
1#
1%
1)
b11001 +
#25000000000000000
0#
0%
0)
#25500000000000000
1#
1%
1)
b11010 +
#26000000000000000
0#
0%
0)
#26500000000000000
1#
1%
1)
b11011 +
#27000000000000000
0#
0%
0)
#27500000000000000
1#
1%
1)
b11100 +
#28000000000000000
0#
0%
0)
#28500000000000000
1#
1%
1)
b11101 +
#29000000000000000
0#
0%
0)
#29500000000000000
1#
1%
1)
b11110 +
#30000000000000000
0#
0%
0)
#30500000000000000
1#
1%
1)
b11111 +
#31000000000000000
0#
0%
0)
#31500000000000000
1#
1%
1)
b100000 +
#32000000000000000
0#
0%
0)
#32500000000000000
1#
1%
1)
b100001 +
#33000000000000000
0#
0%
0)
#33500000000000000
1#
1%
1)
b100010 +
#34000000000000000
0#
0%
0)
#34500000000000000
1#
1%
1)
b100011 +
#35000000000000000
0#
0%
0)
#35500000000000000
1#
1%
1)
b100100 +
#36000000000000000
0#
0%
0)
#36500000000000000
1#
1%
1)
b100101 +
#37000000000000000
0#
0%
0)
#37500000000000000
1#
1%
1)
b100110 +
#38000000000000000
0#
0%
0)
#38500000000000000
1#
1%
1)
b100111 +
#39000000000000000
0#
0%
0)
#39500000000000000
1#
1%
1)
b101000 +
#40000000000000000
0#
0%
0)
#40500000000000000
1#
1%
1)
b101001 +
#41000000000000000
0#
0%
0)
#41500000000000000
1#
1%
1)
b101010 +
#42000000000000000
0#
0%
0)
#42500000000000000
1#
1%
1)
b101011 +
#43000000000000000
0#
0%
0)
#43500000000000000
1#
1%
1)
b101100 +
#44000000000000000
0#
0%
0)
#44500000000000000
1#
1%
1)
b101101 +
#45000000000000000
0#
0%
0)
#45500000000000000
1#
1%
1)
b101110 +
#46000000000000000
0#
0%
0)
#46500000000000000
1#
1%
1)
b101111 +
#47000000000000000
0#
0%
0)
#47500000000000000
1#
1%
1)
b110000 +
#48000000000000000
0#
0%
0)
#48500000000000000
1#
1%
1)
b110001 +
#49000000000000000
0#
0%
0)
#49500000000000000
1#
1%
1)
b110010 +
#50000000000000000
0#
0%
0)
#50500000000000000
1#
1%
1)
b110011 +
#51000000000000000
0#
0%
0)
#51500000000000000
1#
1%
1)
b110100 +
#52000000000000000
0#
0%
0)
#52500000000000000
1#
1%
1)
b110101 +
#53000000000000000
0#
0%
0)
#53500000000000000
1#
1%
1)
b110110 +
#54000000000000000
0#
0%
0)
#54500000000000000
1#
1%
1)
b110111 +
#55000000000000000
0#
0%
0)
#55500000000000000
1#
1%
1)
b111000 +
#56000000000000000
0#
0%
0)
#56500000000000000
1#
1%
1)
b111001 +
#57000000000000000
0#
0%
0)
#57500000000000000
1#
1%
1)
b111010 +
#58000000000000000
0#
0%
0)
#58500000000000000
1#
1%
1)
b111011 +
#59000000000000000
0#
0%
0)
#59500000000000000
1#
1%
1)
b111100 +
#60000000000000000
0#
0%
0)
#60500000000000000
1#
1%
1)
b111101 +
#61000000000000000
0#
0%
0)
#61500000000000000
1#
1%
1)
b111110 +
#62000000000000000
0#
0%
0)
#62500000000000000
1#
1%
1)
b111111 +
#63000000000000000
0#
0%
0)
#63500000000000000
1#
1%
1)
b1000000 +
#64000000000000000
0#
0%
0)
#64500000000000000
1#
1%
1)
b1000001 +
#65000000000000000
0#
0%
0)
#65500000000000000
1#
1%
1)
b1000010 +
#66000000000000000
0#
0%
0)
#66500000000000000
1#
1%
1)
b1000011 +
#67000000000000000
0#
0%
0)
#67500000000000000
1#
1%
1)
b1000100 +
#68000000000000000
0#
0%
0)
#68500000000000000
1#
1%
1)
b1000101 +
#69000000000000000
0#
0%
0)
#69500000000000000
1#
1%
1)
b1000110 +
#70000000000000000
0#
0%
0)
#70500000000000000
1#
1%
1)
b1000111 +
#71000000000000000
0#
0%
0)
#71500000000000000
1#
1%
1)
b1001000 +
#72000000000000000
0#
0%
0)
#72500000000000000
1#
1%
1)
b1001001 +
#73000000000000000
0#
0%
0)
#73500000000000000
1#
1%
1)
b1001010 +
#74000000000000000
0#
0%
0)
#74500000000000000
1#
1%
1)
b1001011 +
#75000000000000000
0#
0%
0)
#75500000000000000
1#
1%
1)
b1001100 +
#76000000000000000
0#
0%
0)
#76500000000000000
1#
1%
1)
b1001101 +
#77000000000000000
0#
0%
0)
#77500000000000000
1#
1%
1)
b1001110 +
#78000000000000000
0#
0%
0)
#78500000000000000
1#
1%
1)
b1001111 +
#79000000000000000
0#
0%
0)
#79500000000000000
1#
1%
1)
b1010000 +
#80000000000000000
0#
0%
0)
#80500000000000000
1#
1%
1)
b1010001 +
#81000000000000000
0#
0%
0)
#81500000000000000
1#
1%
1)
b1010010 +
#82000000000000000
0#
0%
0)
#82500000000000000
1#
1%
1)
b1010011 +
#83000000000000000
0#
0%
0)
#83500000000000000
1#
1%
1)
b1010100 +
#84000000000000000
0#
0%
0)
#84500000000000000
1#
1%
1)
b1010101 +
#85000000000000000
0#
0%
0)
#85500000000000000
1#
1%
1)
b1010110 +
#86000000000000000
0#
0%
0)
#86500000000000000
1#
1%
1)
b1010111 +
#87000000000000000
0#
0%
0)
#87500000000000000
1#
1%
1)
b1011000 +
#88000000000000000
0#
0%
0)
#88500000000000000
1#
1%
1)
b1011001 +
#89000000000000000
0#
0%
0)
#89500000000000000
1#
1%
1)
b1011010 +
#90000000000000000
0#
0%
0)
#90500000000000000
1#
1%
1)
b1011011 +
#91000000000000000
0#
0%
0)
#91500000000000000
1#
1%
1)
b1011100 +
#92000000000000000
0#
0%
0)
#92500000000000000
1#
1%
1)
b1011101 +
#93000000000000000
0#
0%
0)
#93500000000000000
1#
1%
1)
b1011110 +
#94000000000000000
0#
0%
0)
#94500000000000000
1#
1%
1)
b1011111 +
#95000000000000000
0#
0%
0)
#95500000000000000
1#
1%
1)
b1100000 +
#96000000000000000
0#
0%
0)
#96500000000000000
1#
1%
1)
b1100001 +
#97000000000000000
0#
0%
0)
#97500000000000000
1#
1%
1)
b1100010 +
#98000000000000000
0#
0%
0)
#98500000000000000
1#
1%
1)
b1100011 +
#99000000000000000
0#
0%
0)
#99500000000000000
1#
1%
1)
b1100100 +
#100000000000000000
0#
0%
0)
#100500000000000000
1#
1%
1)
b0 +
#101000000000000000
0#
0%
0)
#101500000000000000
1#
1%
1)
b1 +
#102000000000000000
0#
0%
0)
#102500000000000000
1#
1%
1)
b10 +
#103000000000000000
0#
0%
0)
#103500000000000000
1#
1%
1)
b11 +
#104000000000000000
0#
0%
0)
#104500000000000000
1#
1%
1)
b100 +
#105000000000000000
0#
0%
0)
#105500000000000000
1#
1%
1)
b101 +
#106000000000000000
0#
0%
0)
#106500000000000000
1#
1%
1)
b110 +
#107000000000000000
0#
0%
0)
#107500000000000000
1#
1%
1)
b111 +
#108000000000000000
0#
0%
0)
#108500000000000000
1#
1%
1)
b1000 +
#109000000000000000
0#
0%
0)
#109500000000000000
1#
1%
1)
b1001 +
#110000000000000000
0#
0%
0)
#110500000000000000
1#
1%
1)
b1010 +
#111000000000000000
0#
0%
0)
#111500000000000000
1#
1%
1)
b1011 +
#112000000000000000
0#
0%
0)
#112500000000000000
1#
1%
1)
b1100 +
#113000000000000000
0#
0%
0)
#113500000000000000
1#
1%
1)
b1101 +
#114000000000000000
0#
0%
0)
#114500000000000000
1#
1%
1)
b1110 +
#115000000000000000
0#
0%
0)
#115500000000000000
1#
1%
1)
b1111 +
#116000000000000000
0#
0%
0)
#116500000000000000
1#
1%
1)
b10000 +
#117000000000000000
0#
0%
0)
#117500000000000000
1#
1%
1)
b10001 +
#118000000000000000
0#
0%
0)
#118500000000000000
1#
1%
1)
b10010 +
#119000000000000000
0#
0%
0)
#119500000000000000
1#
1%
1)
b10011 +
#120000000000000000
0#
0%
0)
#120500000000000000
1#
1%
1)
b10100 +
#121000000000000000
0#
0%
0)
#121500000000000000
1#
1%
1)
b10101 +
#122000000000000000
0#
0%
0)
#122500000000000000
1#
1%
1)
b10110 +
#123000000000000000
0#
0%
0)
#123500000000000000
1#
1%
1)
b10111 +
#124000000000000000
0#
0%
0)
#124500000000000000
1#
1%
1)
b11000 +
#125000000000000000
0#
0%
0)
#125500000000000000
1#
1%
1)
b11001 +
#126000000000000000
0#
0%
0)
#126500000000000000
1#
1%
1)
b11010 +
#127000000000000000
0#
0%
0)
#127500000000000000
1#
1%
1)
b11011 +
#128000000000000000
0#
0%
0)
#128500000000000000
1#
1%
1)
b11100 +
#129000000000000000
0#
0%
0)
#129500000000000000
1#
1%
1)
b11101 +
#130000000000000000
0#
0%
0)
#130500000000000000
1#
1%
1)
b11110 +
#131000000000000000
0#
0%
0)
#131500000000000000
1#
1%
1)
b11111 +
#132000000000000000
0#
0%
0)
#132500000000000000
1#
1%
1)
b100000 +
#133000000000000000
0#
0%
0)
#133500000000000000
1#
1%
1)
b100001 +
#134000000000000000
0#
0%
0)
#134500000000000000
1#
1%
1)
b100010 +
#135000000000000000
0#
0%
0)
#135500000000000000
1#
1%
1)
b100011 +
#136000000000000000
0#
0%
0)
#136500000000000000
1#
1%
1)
b100100 +
#137000000000000000
0#
0%
0)
#137500000000000000
1#
1%
1)
b100101 +
#138000000000000000
0#
0%
0)
#138500000000000000
1#
1%
1)
b100110 +
#139000000000000000
0#
0%
0)
#139500000000000000
1#
1%
1)
b100111 +
#140000000000000000
0#
0%
0)
#140500000000000000
1#
1%
1)
b101000 +
#141000000000000000
0#
0%
0)
#141500000000000000
1#
1%
1)
b101001 +
#142000000000000000
0#
0%
0)
#142500000000000000
1#
1%
1)
b101010 +
#143000000000000000
0#
0%
0)
#143500000000000000
1#
1%
1)
b101011 +
#144000000000000000
0#
0%
0)
#144500000000000000
1#
1%
1)
b101100 +
#145000000000000000
0#
0%
0)
#145500000000000000
1#
1%
1)
b101101 +
#146000000000000000
0#
0%
0)
#146500000000000000
1#
1%
1)
b101110 +
#147000000000000000
0#
0%
0)
#147500000000000000
1#
1%
1)
b101111 +
#148000000000000000
0#
0%
0)
#148500000000000000
1#
1%
1)
b110000 +
#149000000000000000
0#
0%
0)
#149500000000000000
1#
1%
1)
b110001 +
#150000000000000000
0#
0%
0)
#150500000000000000
1#
1%
1)
b110010 +
#151000000000000000
0#
0%
0)
#151500000000000000
1#
1%
1)
b110011 +
#152000000000000000
0#
0%
0)
#152500000000000000
1#
1%
1)
b110100 +
#153000000000000000
0#
0%
0)
#153500000000000000
1#
1%
1)
b110101 +
#154000000000000000
0#
0%
0)
#154500000000000000
1#
1%
1)
b110110 +
#155000000000000000
0#
0%
0)
#155500000000000000
1#
1%
1)
b110111 +
#156000000000000000
0#
0%
0)
#156500000000000000
1#
1%
1)
b111000 +
#157000000000000000
0#
0%
0)
#157500000000000000
1#
1%
1)
b111001 +
#158000000000000000
0#
0%
0)
#158500000000000000
1#
1%
1)
b111010 +
#159000000000000000
0#
0%
0)
#159500000000000000
1#
1%
1)
b111011 +
#160000000000000000
0#
0%
0)
#160500000000000000
1#
1%
1)
b111100 +
#161000000000000000
0#
0%
0)
#161500000000000000
1#
1%
1)
b111101 +
#162000000000000000
0#
0%
0)
#162500000000000000
1#
1%
1)
b111110 +
#163000000000000000
0#
0%
0)
#163500000000000000
1#
1%
1)
b111111 +
#164000000000000000
0#
0%
0)
#164500000000000000
1#
1%
1)
b1000000 +
#165000000000000000
0#
0%
0)
#165500000000000000
1#
1%
1)
b1000001 +
#166000000000000000
0#
0%
0)
#166500000000000000
1#
1%
1)
b1000010 +
#167000000000000000
0#
0%
0)
#167500000000000000
1#
1%
1)
b1000011 +
#168000000000000000
0#
0%
0)
#168500000000000000
1#
1%
1)
b1000100 +
#169000000000000000
0#
0%
0)
#169500000000000000
1#
1%
1)
b1000101 +
#170000000000000000
0#
0%
0)
#170500000000000000
1#
1%
1)
b1000110 +
#171000000000000000
0#
0%
0)
#171500000000000000
1#
1%
1)
b1000111 +
#172000000000000000
0#
0%
0)
#172500000000000000
1#
1%
1)
b1001000 +
#173000000000000000
0#
0%
0)
#173500000000000000
1#
1%
1)
b1001001 +
#174000000000000000
0#
0%
0)
#174500000000000000
1#
1%
1)
b1001010 +
#175000000000000000
0#
0%
0)
#175500000000000000
1#
1%
1)
b1001011 +
#176000000000000000
0#
0%
0)
#176500000000000000
1#
1%
1)
b1001100 +
#177000000000000000
0#
0%
0)
#177500000000000000
1#
1%
1)
b1001101 +
#178000000000000000
0#
0%
0)
#178500000000000000
1#
1%
1)
b1001110 +
#179000000000000000
0#
0%
0)
#179500000000000000
1#
1%
1)
b1001111 +
#180000000000000000
0#
0%
0)
#180500000000000000
1#
1%
1)
b1010000 +
#181000000000000000
0#
0%
0)
#181500000000000000
1#
1%
1)
b1010001 +
#182000000000000000
0#
0%
0)
#182500000000000000
1#
1%
1)
b1010010 +
#183000000000000000
0#
0%
0)
#183500000000000000
1#
1%
1)
b1010011 +
#184000000000000000
0#
0%
0)
#184500000000000000
1#
1%
1)
b1010100 +
#185000000000000000
0#
0%
0)
#185500000000000000
1#
1%
1)
b1010101 +
#186000000000000000
0#
0%
0)
#186500000000000000
1#
1%
1)
b1010110 +
#187000000000000000
0#
0%
0)
#187500000000000000
1#
1%
1)
b1010111 +
#188000000000000000
0#
0%
0)
#188500000000000000
1#
1%
1)
b1011000 +
#189000000000000000
0#
0%
0)
#189500000000000000
1#
1%
1)
b1011001 +
#190000000000000000
0#
0%
0)
#190500000000000000
1#
1%
1)
b1011010 +
#191000000000000000
0#
0%
0)
#191500000000000000
1#
1%
1)
b1011011 +
#192000000000000000
0#
0%
0)
#192500000000000000
1#
1%
1)
b1011100 +
#193000000000000000
0#
0%
0)
#193500000000000000
1#
1%
1)
b1011101 +
#194000000000000000
0#
0%
0)
#194500000000000000
1#
1%
1)
b1011110 +
#195000000000000000
0#
0%
0)
#195500000000000000
1#
1%
1)
b1011111 +
#196000000000000000
0#
0%
0)
#196500000000000000
1#
1%
1)
b1100000 +
#197000000000000000
0#
0%
0)
#197500000000000000
1#
1%
1)
b1100001 +
#198000000000000000
0#
0%
0)
#198500000000000000
1#
1%
1)
b1100010 +
#199000000000000000
0#
0%
0)
#199500000000000000
1#
1%
1)
b1100011 +
#200000000000000000
0#
0%
0)
#200500000000000000
1#
1%
1)
b1100100 +
#201000000000000000
0#
0%
0)
#201500000000000000
1#
1%
1)
b0 +
#202000000000000000
0#
0%
0)
#202500000000000000
1#
1%
1)
b1 +
#203000000000000000
0#
0%
0)
#203500000000000000
1#
1%
1)
b10 +
#204000000000000000
0#
0%
0)
#204500000000000000
1#
1%
1)
b11 +
#205000000000000000
0#
0%
0)
#205500000000000000
1#
1%
1)
b100 +
#206000000000000000
0#
0%
0)
#206500000000000000
1#
1%
1)
b101 +
#207000000000000000
0#
0%
0)
#207500000000000000
1#
1%
1)
b110 +
#208000000000000000
0#
0%
0)
#208500000000000000
1#
1%
1)
b111 +
#209000000000000000
0#
0%
0)
#209500000000000000
1#
1%
1)
b1000 +
#210000000000000000
0#
0%
0)
#210500000000000000
1#
1%
1)
b1001 +
#211000000000000000
0#
0%
0)
#211500000000000000
1#
1%
1)
b1010 +
#212000000000000000
0#
0%
0)
#212500000000000000
1#
1%
1)
b1011 +
#213000000000000000
0#
0%
0)
#213500000000000000
1#
1%
1)
b1100 +
#214000000000000000
0#
0%
0)
#214500000000000000
1#
1%
1)
b1101 +
#215000000000000000
0#
0%
0)
#215500000000000000
1#
1%
1)
b1110 +
#216000000000000000
0#
0%
0)
#216500000000000000
1#
1%
1)
b1111 +
#217000000000000000
0#
0%
0)
#217500000000000000
1#
1%
1)
b10000 +
#218000000000000000
0#
0%
0)
#218500000000000000
1#
1%
1)
b10001 +
#219000000000000000
0#
0%
0)
#219500000000000000
1#
1%
1)
b10010 +
#220000000000000000
0#
0%
0)
#220500000000000000
1#
1%
1)
b10011 +
#221000000000000000
0#
0%
0)
#221500000000000000
1#
1%
1)
b10100 +
#222000000000000000
0#
0%
0)
#222500000000000000
1#
1%
1)
b10101 +
#223000000000000000
0#
0%
0)
#223500000000000000
1#
1%
1)
b10110 +
#224000000000000000
0#
0%
0)
#224500000000000000
1#
1%
1)
b10111 +
#225000000000000000
0#
0%
0)
#225500000000000000
1#
1%
1)
b11000 +
#226000000000000000
0#
0%
0)
#226500000000000000
1#
1%
1)
b11001 +
#227000000000000000
0#
0%
0)
#227500000000000000
1#
1%
1)
b11010 +
#228000000000000000
0#
0%
0)
#228500000000000000
1#
1%
1)
b11011 +
#229000000000000000
0#
0%
0)
#229500000000000000
1#
1%
1)
b11100 +
#230000000000000000
0#
0%
0)
#230500000000000000
1#
1%
1)
b11101 +
#231000000000000000
0#
0%
0)
#231500000000000000
1#
1%
1)
b11110 +
#232000000000000000
0#
0%
0)
#232500000000000000
1#
1%
1)
b11111 +
#233000000000000000
0#
0%
0)
#233500000000000000
1#
1%
1)
b100000 +
#234000000000000000
0#
0%
0)
#234500000000000000
1#
1%
1)
b100001 +
#235000000000000000
0#
0%
0)
#235500000000000000
1#
1%
1)
b100010 +
#236000000000000000
0#
0%
0)
#236500000000000000
1#
1%
1)
b100011 +
#237000000000000000
0#
0%
0)
#237500000000000000
1#
1%
1)
b100100 +
#238000000000000000
0#
0%
0)
#238500000000000000
1#
1%
1)
b100101 +
#239000000000000000
0#
0%
0)
#239500000000000000
1#
1%
1)
b100110 +
#240000000000000000
0#
0%
0)
#240500000000000000
1#
1%
1)
b100111 +
#241000000000000000
0#
0%
0)
#241500000000000000
1#
1%
1)
b101000 +
#242000000000000000
0#
0%
0)
#242500000000000000
1#
1%
1)
b101001 +
#243000000000000000
0#
0%
0)
#243500000000000000
1#
1%
1)
b101010 +
#244000000000000000
0#
0%
0)
#244500000000000000
1#
1%
1)
b101011 +
#245000000000000000
0#
0%
0)
#245500000000000000
1#
1%
1)
b101100 +
#246000000000000000
0#
0%
0)
#246500000000000000
1#
1%
1)
b101101 +
#247000000000000000
0#
0%
0)
#247500000000000000
1#
1%
1)
b101110 +
#248000000000000000
0#
0%
0)
#248500000000000000
1#
1%
1)
b101111 +
#249000000000000000
0#
0%
0)
#249500000000000000
1#
1%
1)
b110000 +
#250000000000000000
0#
0%
0)
#250500000000000000
1#
1%
1)
b110001 +
#251000000000000000
0#
0%
0)
#251500000000000000
1#
1%
1)
b110010 +
#252000000000000000
0#
0%
0)
#252500000000000000
1#
1%
1)
b110011 +
#253000000000000000
0#
0%
0)
#253500000000000000
1#
1%
1)
b110100 +
#254000000000000000
0#
0%
0)
#254500000000000000
1#
1%
1)
b110101 +
#255000000000000000
0#
0%
0)
#255500000000000000
1#
1%
1)
b110110 +
#256000000000000000
0#
0%
0)
#256500000000000000
1#
1%
1)
b110111 +
#257000000000000000
0#
0%
0)
#257500000000000000
1#
1%
1)
b111000 +
#258000000000000000
0#
0%
0)
#258500000000000000
1#
1%
1)
b111001 +
#259000000000000000
0#
0%
0)
#259500000000000000
1#
1%
1)
b111010 +
#260000000000000000
0#
0%
0)
#260500000000000000
1#
1%
1)
b111011 +
#261000000000000000
0#
0%
0)
#261500000000000000
1#
1%
1)
b111100 +
#262000000000000000
0#
0%
0)
#262500000000000000
1#
1%
1)
b111101 +
#263000000000000000
0#
0%
0)
#263500000000000000
1#
1%
1)
b111110 +
#264000000000000000
0#
0%
0)
#264500000000000000
1#
1%
1)
b111111 +
#265000000000000000
0#
0%
0)
#265500000000000000
1#
1%
1)
b1000000 +
#266000000000000000
0#
0%
0)
#266500000000000000
1#
1%
1)
b1000001 +
#267000000000000000
0#
0%
0)
#267500000000000000
1#
1%
1)
b1000010 +
#268000000000000000
0#
0%
0)
#268500000000000000
1#
1%
1)
b1000011 +
#269000000000000000
0#
0%
0)
#269500000000000000
1#
1%
1)
b1000100 +
#270000000000000000
0#
0%
0)
#270500000000000000
1#
1%
1)
b1000101 +
#271000000000000000
0#
0%
0)
#271500000000000000
1#
1%
1)
b1000110 +
#272000000000000000
0#
0%
0)
#272500000000000000
1#
1%
1)
b1000111 +
#273000000000000000
0#
0%
0)
#273500000000000000
1#
1%
1)
b1001000 +
#274000000000000000
0#
0%
0)
#274500000000000000
1#
1%
1)
b1001001 +
#275000000000000000
0#
0%
0)
#275500000000000000
1#
1%
1)
b1001010 +
#276000000000000000
0#
0%
0)
#276500000000000000
1#
1%
1)
b1001011 +
#277000000000000000
0#
0%
0)
#277500000000000000
1#
1%
1)
b1001100 +
#278000000000000000
0#
0%
0)
#278500000000000000
1#
1%
1)
b1001101 +
#279000000000000000
0#
0%
0)
#279500000000000000
1#
1%
1)
b1001110 +
#280000000000000000
0#
0%
0)
#280500000000000000
1#
1%
1)
b1001111 +
#281000000000000000
0#
0%
0)
#281500000000000000
1#
1%
1)
b1010000 +
#282000000000000000
0#
0%
0)
#282500000000000000
1#
1%
1)
b1010001 +
#283000000000000000
0#
0%
0)
#283500000000000000
1#
1%
1)
b1010010 +
#284000000000000000
0#
0%
0)
#284500000000000000
1#
1%
1)
b1010011 +
#285000000000000000
0#
0%
0)
#285500000000000000
1#
1%
1)
b1010100 +
#286000000000000000
0#
0%
0)
#286500000000000000
1#
1%
1)
b1010101 +
#287000000000000000
0#
0%
0)
#287500000000000000
1#
1%
1)
b1010110 +
#288000000000000000
0#
0%
0)
#288500000000000000
1#
1%
1)
b1010111 +
#289000000000000000
0#
0%
0)
#289500000000000000
1#
1%
1)
b1011000 +
#290000000000000000
0#
0%
0)
#290500000000000000
1#
1%
1)
b1011001 +
#291000000000000000
0#
0%
0)
#291500000000000000
1#
1%
1)
b1011010 +
#292000000000000000
0#
0%
0)
#292500000000000000
1#
1%
1)
b1011011 +
#293000000000000000
0#
0%
0)
#293500000000000000
1#
1%
1)
b1011100 +
#294000000000000000
0#
0%
0)
#294500000000000000
1#
1%
1)
b1011101 +
#295000000000000000
0#
0%
0)
#295500000000000000
1#
1%
1)
b1011110 +
#296000000000000000
0#
0%
0)
#296500000000000000
1#
1%
1)
b1011111 +
#297000000000000000
0#
0%
0)
#297500000000000000
1#
1%
1)
b1100000 +
#298000000000000000
0#
0%
0)
#298500000000000000
1#
1%
1)
b1100001 +
#299000000000000000
0#
0%
0)
#299500000000000000
1#
1%
1)
b1100010 +
#300000000000000000
0#
0%
0)
#300500000000000000
1#
1%
1)
b1100011 +
#301000000000000000
0#
0%
0)
#301500000000000000
1#
1%
1)
b1100100 +
#302000000000000000
0#
0%
0)
#302500000000000000
1#
1%
1)
b0 +
#303000000000000000
0#
0%
0)
#303500000000000000
1#
1%
1)
b1 +
#304000000000000000
0#
0%
0)
#304500000000000000
1#
1%
1)
b10 +
#305000000000000000
0#
0%
0)
#305500000000000000
1#
1%
1)
b11 +
#306000000000000000
0#
0%
0)
#306500000000000000
1#
1%
1)
b100 +
#307000000000000000
0#
0%
0)
#307500000000000000
1#
1%
1)
b101 +
#308000000000000000
0#
0%
0)
#308500000000000000
1#
1%
1)
b110 +
#309000000000000000
0#
0%
0)
#309500000000000000
1#
1%
1)
b111 +
#310000000000000000
0#
0%
0)
#310500000000000000
1#
1%
1)
b1000 +
#311000000000000000
0#
0%
0)
#311500000000000000
1#
1%
1)
b1001 +
#312000000000000000
0#
0%
0)
#312500000000000000
1#
1%
1)
b1010 +
#313000000000000000
0#
0%
0)
#313500000000000000
1#
1%
1)
b1011 +
#314000000000000000
0#
0%
0)
#314500000000000000
1#
1%
1)
b1100 +
#315000000000000000
0#
0%
0)
#315500000000000000
1#
1%
1)
b1101 +
#316000000000000000
0#
0%
0)
#316500000000000000
1#
1%
1)
b1110 +
#317000000000000000
0#
0%
0)
#317500000000000000
1#
1%
1)
b1111 +
#318000000000000000
0#
0%
0)
#318500000000000000
1#
1%
1)
b10000 +
#319000000000000000
0#
0%
0)
#319500000000000000
1#
1%
1)
b10001 +
#320000000000000000
0#
0%
0)
#320500000000000000
1#
1%
1)
b10010 +
#321000000000000000
0#
0%
0)
#321500000000000000
1#
1%
1)
b10011 +
#322000000000000000
0#
0%
0)
#322500000000000000
1#
1%
1)
b10100 +
#323000000000000000
0#
0%
0)
#323500000000000000
1#
1%
1)
b10101 +
#324000000000000000
0#
0%
0)
#324500000000000000
1#
1%
1)
b10110 +
#325000000000000000
0#
0%
0)
#325500000000000000
1#
1%
1)
b10111 +
#326000000000000000
0#
0%
0)
